sendkeysonroids/LICENSE.txt
sendkeysonroids/README.MD
sendkeysonroids/__init__.py
sendkeysonroids/requirements.txt
sendkeysonroids/thirdparty.json
sendkeysonroids-0.10.dist-info/LICENSE.rst
sendkeysonroids-0.10.dist-info/METADATA
sendkeysonroids-0.10.dist-info/WHEEL
sendkeysonroids-0.10.dist-info/top_level.txt
sendkeysonroids-0.10.dist-info/RECORD
